{
  "items": [
    {
      "asin": "B0FKQ5HWBN",
      "title": "Creatina, Mais Mu, Sem Sabor, 100% Pura, Mais Força e Desempenho – 500g",
      "date": "2025-12-25T21:38:09.296Z"
    },
    {
      "asin": "B0CLQLFXWD",
      "title": "Creatine Turbo BlackSkull - Creatina Monohidratada em pó, com carboidrato para melhor absorção e performance (300g Refil, Sem sabor)",
      "date": "2025-12-25T21:40:52.617Z"
    },
    {
      "asin": "B0DHSS7W8P",
      "date": "2025-12-25T23:34:38.327Z"
    }
  ]
}